sass_styleguide/__init__.py
sass_styleguide/scss.py
sass_styleguide-0.1.3.data/scripts/sass-styleguide
sass_styleguide-0.1.3.dist-info/DESCRIPTION.rst
sass_styleguide-0.1.3.dist-info/METADATA
sass_styleguide-0.1.3.dist-info/RECORD
sass_styleguide-0.1.3.dist-info/WHEEL
sass_styleguide-0.1.3.dist-info/metadata.json
sass_styleguide-0.1.3.dist-info/top_level.txt
