Metadata-Version: 2.0
Name: sass-styleguide
Version: 0.1.3
Summary: Generates a static html page displaying information about your Sass files
Home-page: https://github.com/igniteflow/sass-styleguide
Author: Phil Tysoe
Author-email: philtysoe@gmail.com
License: MIT
Platform: UNKNOWN
Requires-Dist: Jinja2
